LICENSE
MANIFEST.in
NOTICE
README.md
setup.cfg
setup.py
cytomine_pims.egg-info/PKG-INFO
cytomine_pims.egg-info/SOURCES.txt
cytomine_pims.egg-info/dependency_links.txt
cytomine_pims.egg-info/requires.txt
cytomine_pims.egg-info/top_level.txt
pims/__init__.py
pims/__version__.py
pims/application.py
pims/config.py
pims/docs.py
pims/fastapi_tweaks.py
pims/logger.py
pims/main.py
pims/api/__init__.py
pims/api/annotation.py
pims/api/colormaps.py
pims/api/exceptions.py
pims/api/filters.py
pims/api/formats.py
pims/api/histograms.py
pims/api/housekeeping.py
pims/api/metadata.py
pims/api/operations.py
pims/api/resized.py
pims/api/server.py
pims/api/spectral.py
pims/api/thumb.py
pims/api/tile.py
pims/api/window.py
pims/api/utils/__init__.py
pims/api/utils/annotation_parameter.py
pims/api/utils/cytomine_auth.py
pims/api/utils/header.py
pims/api/utils/input_parameter.py
pims/api/utils/mimetype.py
pims/api/utils/models.py
pims/api/utils/output_parameter.py
pims/api/utils/parameter.py
pims/api/utils/processing_parameter.py
pims/api/utils/range_parameter.py
pims/api/utils/response.py
pims/cache/__init__.py
pims/cache/memory.py
pims/cache/object.py
pims/cache/redis.py
pims/files/__init__.py
pims/files/archive.py
pims/files/file.py
pims/files/histogram.py
pims/files/image.py
pims/filters/__init__.py
pims/filters/global_histogram.py
pims/filters/pixel_color_deconvolution.py
pims/formats/__init__.py
pims/formats/common/__init__.py
pims/formats/common/bmp.py
pims/formats/common/dicom.py
pims/formats/common/imagej.py
pims/formats/common/jpeg.py
pims/formats/common/jpeg2000.py
pims/formats/common/ometiff.py
pims/formats/common/png.py
pims/formats/common/ppm.py
pims/formats/common/sis.py
pims/formats/common/tiff.py
pims/formats/common/virtual.py
pims/formats/common/webp.py
pims/formats/utils/__init__.py
pims/formats/utils/abstract.py
pims/formats/utils/checker.py
pims/formats/utils/convertor.py
pims/formats/utils/factories.py
pims/formats/utils/histogram.py
pims/formats/utils/parser.py
pims/formats/utils/reader.py
pims/formats/utils/engines/__init__.py
pims/formats/utils/engines/exiftool.py
pims/formats/utils/engines/omexml.py
pims/formats/utils/engines/pil.py
