Metadata-Version: 2.1
Name: cytomine-pims
Version: 0.14.0
Summary: Cytomine Python Image Server
Home-page: https://doc.uliege.cytomine.org
Author: Ulysse Rubens
Author-email: uliege@cytomine.org
License: Apache 2.0
Platform: UNKNOWN
Classifier: License :: OSI Approved :: Apache Software License
Classifier: Programming Language :: Python
Classifier: Programming Language :: Python :: 3
Classifier: Programming Language :: Python :: 3.8
Classifier: Programming Language :: Python :: 3.9
Classifier: Programming Language :: Python :: Implementation :: CPython
Requires-Python: >=3.8.0
Provides-Extra: tests
License-File: LICENSE
License-File: NOTICE
